{"data":{"695634865":[{"s":0,"ids":["JEDIMASTERKENOBI","COMMANDERAHSOKA","GENERALKENOBI","GENERALSKYWALKER","AHSOKATANO"]},{"ids":["COMMANDERLUKESKYWALKER","C3POLEGENDARY","HANSOLO","CHEWBACCALEGENDARY","C3POCHEWBACCA"],"s":0},{"s":0,"ids":["GRANDMASTERLUKE","JEDIKNIGHTLUKE","JEDIKNIGHTREVAN","GRANDMASTERYODA","HERMITYODA"]},{"s":0,"ids":["PADMEAMIDALA","BADBATCHHUNTER","BADBATCHECHO","BADBATCHTECH","BADBATCHWRECKER"]},{"s":12,"ids":["EMPERORPALPATINE","MARAJADE","VADER","GRANDADMIRALTHRAWN","ROYALGUARD"]},{"ids":["VEERS","ADMIRALPIETT","DARKTROOPER","RANGETROOPER","COLONELSTARCK"],"s":38},{"s":0,"ids":["EMPERORPALPATINE","MARAJADE","VADER","GRANDADMIRALTHRAWN","DARTHMALAK"]}],"619735683":[{"s":19,"ids":["EMPERORPALPATINE","MARAJADE","VADER","GRANDADMIRALTHRAWN","DARTHMALAK"]},{"ids":["VEERS","ADMIRALPIETT","DARKTROOPER","RANGETROOPER","COLONELSTARCK"],"s":6},{"ids":["COMMANDERLUKESKYWALKER","C3POLEGENDARY","HANSOLO","CHEWBACCALEGENDARY","C3POCHEWBACCA"],"s":11},{"s":2,"ids":["GRANDMASTERLUKE","JEDIKNIGHTLUKE","JEDIKNIGHTREVAN","GRANDMASTERYODA","HERMITYODA"]}],"837692324":[{"s":0,"ids":["GRANDMASTERLUKE","JEDIKNIGHTLUKE","JEDIKNIGHTREVAN","GRANDMASTERYODA","HERMITYODA"]},{"ids":["EMPERORPALPATINE","MARAJADE","VADER","GRANDADMIRALTHRAWN","DARTHMALAK"],"s":0},{"s":0,"ids":["COMMANDERLUKESKYWALKER","C3POLEGENDARY","HANSOLO","CHEWBACCALEGENDARY","C3POCHEWBACCA"]},{"ids":["VEERS","ADMIRALPIETT","DARKTROOPER","RANGETROOPER","COLONELSTARCK"],"s":26},{"s":41,"ids":["PADMEAMIDALA","BADBATCHHUNTER","BADBATCHECHO","BADBATCHTECH","BADBATCHWRECKER"]},{"ids":["JEDIMASTERKENOBI","COMMANDERAHSOKA","GENERALKENOBI","GENERALSKYWALKER","AHSOKATANO"],"s":17}],"539764381":[{"s":14,"ids":["COMMANDERLUKESKYWALKER","C3POLEGENDARY","HANSOLO","CHEWBACCALEGENDARY","C3POCHEWBACCA"]},{"s":13,"ids":["EMPERORPALPATINE","MARAJADE","VADER","GRANDADMIRALTHRAWN","ROYALGUARD"]},{"ids":["PADMEAMIDALA","BADBATCHHUNTER","BADBATCHECHO","BADBATCHTECH","BADBATCHWRECKER"],"s":32},{"ids":["EMPERORPALPATINE","MARAJADE","VADER","GRANDADMIRALTHRAWN","DARTHMALAK"],"s":13},{"ids":["GRANDMASTERLUKE","JEDIKNIGHTLUKE","JEDIKNIGHTREVAN","GRANDMASTERYODA","HERMITYODA"],"s":9},{"s":34,"ids":["VEERS","ADMIRALPIETT","DARKTROOPER","RANGETROOPER","COLONELSTARCK"]}],"148488677":[{"s":0,"ids":["COMMANDERLUKESKYWALKER","C3POLEGENDARY","HANSOLO","CHEWBACCALEGENDARY","C3POCHEWBACCA"]},{"ids":["GRANDMASTERLUKE","JEDIKNIGHTLUKE","JEDIKNIGHTREVAN","GRANDMASTERYODA","HERMITYODA"],"s":6},{"ids":["EMPERORPALPATINE","MARAJADE","VADER","GRANDADMIRALTHRAWN","ROYALGUARD"],"s":19},{"ids":["JEDIMASTERKENOBI","COMMANDERAHSOKA","GENERALKENOBI","GENERALSKYWALKER","AHSOKATANO"],"s":27},{"ids":["PADMEAMIDALA","BADBATCHHUNTER","BADBATCHECHO","BADBATCHTECH","BADBATCHWRECKER"],"s":47}],"836516255":[{"ids":["EMPERORPALPATINE","MARAJADE","VADER","GRANDADMIRALTHRAWN","ROYALGUARD"],"s":16},{"s":14,"ids":["COMMANDERLUKESKYWALKER","C3POLEGENDARY","HANSOLO","CHEWBACCALEGENDARY","C3POCHEWBACCA"]},{"ids":["PADMEAMIDALA","BADBATCHHUNTER","BADBATCHECHO","BADBATCHTECH","BADBATCHWRECKER"],"s":40},{"ids":["VEERS","ADMIRALPIETT","DARKTROOPER","RANGETROOPER","MOFFGIDEONS1"],"s":35},{"s":24,"ids":["VEERS","ADMIRALPIETT","DARKTROOPER","RANGETROOPER","COLONELSTARCK"]}],"759183489":[{"s":0,"ids":["COMMANDERLUKESKYWALKER","C3POLEGENDARY","HANSOLO","CHEWBACCALEGENDARY","C3POCHEWBACCA"]},{"s":2,"ids":["EMPERORPALPATINE","MARAJADE","VADER","GRANDADMIRALTHRAWN","DARTHMALAK"]},{"s":18,"ids":["VEERS","ADMIRALPIETT","DARKTROOPER","RANGETROOPER","COLONELSTARCK"]},{"ids":["PADMEAMIDALA","BADBATCHHUNTER","BADBATCHECHO","BADBATCHTECH","BADBATCHWRECKER"],"s":44}],"742792457":[{"s":0,"ids":["COMMANDERLUKESKYWALKER","C3POLEGENDARY","HANSOLO","CHEWBACCALEGENDARY","C3POCHEWBACCA"]},{"s":2,"ids":["EMPERORPALPATINE","MARAJADE","VADER","GRANDADMIRALTHRAWN","DARTHMALAK"]},{"s":32,"ids":["VEERS","ADMIRALPIETT","DARKTROOPER","RANGETROOPER","COLONELSTARCK"]},{"ids":["GRANDMASTERLUKE","JEDIKNIGHTLUKE","JEDIKNIGHTREVAN","GRANDMASTERYODA","HERMITYODA"],"s":6}],"478314836":[{"ids":["GRANDMASTERLUKE","JEDIKNIGHTLUKE","JEDIKNIGHTREVAN","GRANDMASTERYODA","HERMITYODA"],"s":0},{"ids":["COMMANDERLUKESKYWALKER","C3POLEGENDARY","HANSOLO","CHEWBACCALEGENDARY","C3POCHEWBACCA"],"s":0},{"s":13,"ids":["EMPERORPALPATINE","MARAJADE","VADER","GRANDADMIRALTHRAWN","DARTHMALAK"]},{"s":21,"ids":["VEERS","ADMIRALPIETT","DARKTROOPER","RANGETROOPER","MOFFGIDEONS1"]},{"s":44,"ids":["PADMEAMIDALA","BADBATCHHUNTER","BADBATCHECHO","BADBATCHTECH","BADBATCHWRECKER"]},{"s":8,"ids":["JEDIMASTERKENOBI","COMMANDERAHSOKA","GENERALKENOBI","GENERALSKYWALKER","AHSOKATANO"]}],"715365225":[{"ids":["GRANDMASTERLUKE","JEDIKNIGHTLUKE","JEDIKNIGHTREVAN","GRANDMASTERYODA","HERMITYODA"],"s":0},{"s":0,"ids":["COMMANDERLUKESKYWALKER","C3POLEGENDARY","HANSOLO","CHEWBACCALEGENDARY","C3POCHEWBACCA"]},{"s":10,"ids":["EMPERORPALPATINE","MARAJADE","VADER","GRANDADMIRALTHRAWN","DARTHMALAK"]},{"s":24,"ids":["VEERS","ADMIRALPIETT","DARKTROOPER","RANGETROOPER","COLONELSTARCK"]},{"ids":["PADMEAMIDALA","BADBATCHHUNTER","BADBATCHECHO","BADBATCHTECH","BADBATCHWRECKER"],"s":38},{"ids":["JEDIMASTERKENOBI","COMMANDERAHSOKA","GENERALKENOBI","GENERALSKYWALKER","AHSOKATANO"],"s":12}],"146984638":[{"ids":["COMMANDERLUKESKYWALKER","C3POLEGENDARY","HANSOLO","CHEWBACCALEGENDARY","C3POCHEWBACCA"],"s":7},{"s":18,"ids":["EMPERORPALPATINE","MARAJADE","VADER","GRANDADMIRALTHRAWN","DARTHMALAK"]},{"s":34,"ids":["VEERS","ADMIRALPIETT","DARKTROOPER","RANGETROOPER","MOFFGIDEONS1"]},{"s":38,"ids":["PADMEAMIDALA","BADBATCHHUNTER","BADBATCHECHO","BADBATCHTECH","BADBATCHWRECKER"]}],"683679824":[{"ids":["GRANDMASTERLUKE","JEDIKNIGHTLUKE","JEDIKNIGHTREVAN","GRANDMASTERYODA","HERMITYODA"],"s":1},{"s":1,"ids":["COMMANDERLUKESKYWALKER","C3POLEGENDARY","HANSOLO","CHEWBACCALEGENDARY","C3POCHEWBACCA"]},{"s":14,"ids":["EMPERORPALPATINE","MARAJADE","VADER","GRANDADMIRALTHRAWN","DARTHMALAK"]},{"s":27,"ids":["VEERS","ADMIRALPIETT","DARKTROOPER","RANGETROOPER","COLONELSTARCK"]},{"s":49,"ids":["PADMEAMIDALA","BADBATCHHUNTER","BADBATCHECHO","BADBATCHTECH","BADBATCHWRECKER"]}],"711271515":[{"s":0,"ids":["GRANDMASTERLUKE","JEDIKNIGHTLUKE","JEDIKNIGHTREVAN","GRANDMASTERYODA","HERMITYODA"]},{"s":0,"ids":["COMMANDERLUKESKYWALKER","C3POLEGENDARY","HANSOLO","CHEWBACCALEGENDARY","C3POCHEWBACCA"]},{"ids":["EMPERORPALPATINE","MARAJADE","VADER","GRANDADMIRALTHRAWN","DARTHMALAK"],"s":9},{"s":17,"ids":["VEERS","ADMIRALPIETT","DARKTROOPER","RANGETROOPER","COLONELSTARCK"]},{"ids":["PADMEAMIDALA","BADBATCHHUNTER","BADBATCHECHO","BADBATCHTECH","BADBATCHWRECKER"],"s":34},{"s":10,"ids":["JEDIMASTERKENOBI","COMMANDERAHSOKA","GENERALKENOBI","GENERALSKYWALKER","AHSOKATANO"]}],"271337338":[{"ids":["GRANDMASTERLUKE","JEDIKNIGHTLUKE","JEDIKNIGHTREVAN","GRANDMASTERYODA","HERMITYODA"],"s":2},{"s":2,"ids":["COMMANDERLUKESKYWALKER","C3POLEGENDARY","HANSOLO","CHEWBACCALEGENDARY","C3POCHEWBACCA"]},{"ids":["EMPERORPALPATINE","MARAJADE","VADER","GRANDADMIRALTHRAWN","DARTHMALAK"],"s":18}],"983369611":[{"s":0,"ids":["JEDIMASTERKENOBI","COMMANDERAHSOKA","GENERALKENOBI","GENERALSKYWALKER","AHSOKATANO"]},{"ids":["GRANDMASTERLUKE","JEDIKNIGHTLUKE","JEDIKNIGHTREVAN","GRANDMASTERYODA","HERMITYODA"],"s":0},{"s":0,"ids":["SITHPALPATINE","DARTHMALAK","DARTHMALGUS","BASTILASHANDARK","DARTHREVAN"]},{"ids":["COMMANDERLUKESKYWALKER","C3POLEGENDARY","HANSOLO","CHEWBACCALEGENDARY","C3POCHEWBACCA"],"s":0},{"ids":["EMPERORPALPATINE","MARAJADE","VADER","GRANDADMIRALTHRAWN","ROYALGUARD"],"s":2},{"ids":["VEERS","ADMIRALPIETT","DARKTROOPER","RANGETROOPER","MOFFGIDEONS1"],"s":6},{"ids":["PADMEAMIDALA","BADBATCHHUNTER","BADBATCHECHO","BADBATCHTECH","BADBATCHWRECKER"],"s":44}],"564121831":[{"s":0,"ids":["JEDIMASTERKENOBI","COMMANDERAHSOKA","GENERALKENOBI","GENERALSKYWALKER","AHSOKATANO"]},{"ids":["GRANDMASTERLUKE","JEDIKNIGHTLUKE","JEDIKNIGHTREVAN","GRANDMASTERYODA","HERMITYODA"],"s":0},{"s":0,"ids":["COMMANDERLUKESKYWALKER","C3POLEGENDARY","HANSOLO","CHEWBACCALEGENDARY","C3POCHEWBACCA"]},{"s":0,"ids":["VEERS","ADMIRALPIETT","DARKTROOPER","RANGETROOPER","MOFFGIDEONS1"]},{"ids":["EMPERORPALPATINE","MARAJADE","VADER","GRANDADMIRALTHRAWN","DARTHMALAK"],"s":2},{"s":39,"ids":["PADMEAMIDALA","BADBATCHHUNTER","BADBATCHECHO","BADBATCHTECH","BADBATCHWRECKER"]}],"457797887":[{"s":0,"ids":["JEDIMASTERKENOBI","COMMANDERAHSOKA","GENERALKENOBI","GENERALSKYWALKER","AHSOKATANO"]},{"ids":["EMPERORPALPATINE","MARAJADE","VADER","GRANDADMIRALTHRAWN","DARTHMALAK"],"s":0},{"ids":["VEERS","ADMIRALPIETT","DARKTROOPER","RANGETROOPER","COLONELSTARCK"],"s":2},{"ids":["COMMANDERLUKESKYWALKER","C3POLEGENDARY","HANSOLO","CHEWBACCALEGENDARY","C3POCHEWBACCA"],"s":6},{"ids":["PADMEAMIDALA","BADBATCHHUNTER","BADBATCHECHO","BADBATCHTECH","BADBATCHWRECKER"],"s":50}],"946369416":[{"ids":["COMMANDERLUKESKYWALKER","C3POLEGENDARY","HANSOLO","CHEWBACCALEGENDARY","C3POCHEWBACCA"],"s":0},{"ids":["GRANDMASTERLUKE","JEDIKNIGHTLUKE","JEDIKNIGHTREVAN","GRANDMASTERYODA","HERMITYODA"],"s":0},{"ids":["EMPERORPALPATINE","MARAJADE","VADER","GRANDADMIRALTHRAWN","DARTHMALAK"],"s":8},{"s":24,"ids":["VEERS","ADMIRALPIETT","DARKTROOPER","RANGETROOPER","MOFFGIDEONS1"]},{"ids":["PADMEAMIDALA","BADBATCHHUNTER","BADBATCHECHO","BADBATCHTECH","BADBATCHWRECKER"],"s":39}],"788859343":[{"s":3,"ids":["JEDIMASTERKENOBI","COMMANDERAHSOKA","GENERALKENOBI","GENERALSKYWALKER","AHSOKATANO"]},{"ids":["COMMANDERLUKESKYWALKER","C3POLEGENDARY","HANSOLO","CHEWBACCALEGENDARY","C3POCHEWBACCA"],"s":10},{"s":33,"ids":["EMPERORPALPATINE","MARAJADE","VADER","GRANDADMIRALTHRAWN","DARTHMALAK"]},{"ids":["PADMEAMIDALA","BADBATCHHUNTER","BADBATCHECHO","BADBATCHTECH","BADBATCHWRECKER"],"s":48},{"s":49,"ids":["VEERS","ADMIRALPIETT","DARKTROOPER","RANGETROOPER","MOFFGIDEONS1"]},{"s":7,"ids":["GRANDMASTERLUKE","JEDIKNIGHTLUKE","JEDIKNIGHTREVAN","GRANDMASTERYODA","HERMITYODA"]}],"458163314":[{"ids":["EMPERORPALPATINE","MARAJADE","VADER","GRANDADMIRALTHRAWN","DARTHMALAK"],"s":16},{"ids":["PADMEAMIDALA","BADBATCHHUNTER","BADBATCHECHO","BADBATCHTECH","BADBATCHWRECKER"],"s":50}],"497215141":[{"s":15,"ids":["EMPERORPALPATINE","MARAJADE","VADER","GRANDADMIRALTHRAWN","DARTHMALAK"]},{"ids":["VEERS","ADMIRALPIETT","DARKTROOPER","RANGETROOPER","COLONELSTARCK"],"s":12},{"ids":["COMMANDERLUKESKYWALKER","C3POLEGENDARY","HANSOLO","CHEWBACCALEGENDARY","C3POCHEWBACCA"],"s":15},{"s":39,"ids":["PADMEAMIDALA","BADBATCHHUNTER","BADBATCHECHO","BADBATCHTECH","BADBATCHWRECKER"]},{"s":16,"ids":["GRANDMASTERLUKE","JEDIKNIGHTLUKE","JEDIKNIGHTREVAN","GRANDMASTERYODA","HERMITYODA"]},{"ids":["JEDIMASTERKENOBI","COMMANDERAHSOKA","GENERALKENOBI","GENERALSKYWALKER","AHSOKATANO"],"s":8}],"297469325":[{"ids":["EMPERORPALPATINE","MARAJADE","VADER","GRANDADMIRALTHRAWN","ROYALGUARD"],"s":2},{"s":38,"ids":["PADMEAMIDALA","BADBATCHHUNTER","BADBATCHECHO","BADBATCHTECH","BADBATCHWRECKER"]},{"ids":["JEDIMASTERKENOBI","COMMANDERAHSOKA","GENERALKENOBI","GENERALSKYWALKER","AHSOKATANO"],"s":24},{"ids":["EMPERORPALPATINE","MARAJADE","VADER","GRANDADMIRALTHRAWN","DARTHMALAK"],"s":2},{"ids":["COMMANDERLUKESKYWALKER","C3POLEGENDARY","HANSOLO","CHEWBACCALEGENDARY","C3POCHEWBACCA"],"s":24},{"ids":["VEERS","ADMIRALPIETT","DARKTROOPER","RANGETROOPER","COLONELSTARCK"],"s":22},{"ids":["VEERS","ADMIRALPIETT","DARKTROOPER","RANGETROOPER","MOFFGIDEONS1"],"s":19},{"s":2,"ids":["GRANDMASTERLUKE","JEDIKNIGHTLUKE","JEDIKNIGHTREVAN","GRANDMASTERYODA","HERMITYODA"]}],"668313584":[{"ids":["COMMANDERLUKESKYWALKER","C3POLEGENDARY","HANSOLO","CHEWBACCALEGENDARY","C3POCHEWBACCA"],"s":8},{"s":22,"ids":["EMPERORPALPATINE","MARAJADE","VADER","GRANDADMIRALTHRAWN","DARTHMALAK"]},{"s":45,"ids":["PADMEAMIDALA","BADBATCHHUNTER","BADBATCHECHO","BADBATCHTECH","BADBATCHWRECKER"]},{"s":13,"ids":["GRANDMASTERLUKE","JEDIKNIGHTLUKE","JEDIKNIGHTREVAN","GRANDMASTERYODA","HERMITYODA"]},{"ids":["VEERS","ADMIRALPIETT","DARKTROOPER","RANGETROOPER","COLONELSTARCK"],"s":50},{"s":8,"ids":["EMPERORPALPATINE","MARAJADE","VADER","GRANDADMIRALTHRAWN","ROYALGUARD"]}],"681589517":[{"ids":["EMPERORPALPATINE","MARAJADE","VADER","GRANDADMIRALTHRAWN","DARTHMALAK"],"s":0},{"ids":["COMMANDERLUKESKYWALKER","C3POLEGENDARY","HANSOLO","CHEWBACCALEGENDARY","C3POCHEWBACCA"],"s":9},{"ids":["GRANDMASTERLUKE","JEDIKNIGHTLUKE","JEDIKNIGHTREVAN","GRANDMASTERYODA","HERMITYODA"],"s":0},{"s":11,"ids":["JEDIMASTERKENOBI","COMMANDERAHSOKA","GENERALKENOBI","GENERALSKYWALKER","AHSOKATANO"]}],"913691213":[{"s":4,"ids":["JEDIMASTERKENOBI","COMMANDERAHSOKA","GENERALKENOBI","GENERALSKYWALKER","AHSOKATANO"]},{"s":16,"ids":["EMPERORPALPATINE","MARAJADE","VADER","GRANDADMIRALTHRAWN","DARTHMALAK"]},{"s":32,"ids":["VEERS","ADMIRALPIETT","DARKTROOPER","RANGETROOPER","COLONELSTARCK"]},{"s":38,"ids":["PADMEAMIDALA","BADBATCHHUNTER","BADBATCHECHO","BADBATCHTECH","BADBATCHWRECKER"]},{"ids":["COMMANDERLUKESKYWALKER","C3POLEGENDARY","HANSOLO","CHEWBACCALEGENDARY","C3POCHEWBACCA"],"s":19}],"847959864":[{"ids":["JEDIMASTERKENOBI","COMMANDERAHSOKA","GENERALKENOBI","GENERALSKYWALKER","AHSOKATANO"],"s":0},{"s":0,"ids":["COMMANDERLUKESKYWALKER","C3POLEGENDARY","HANSOLO","CHEWBACCALEGENDARY","C3POCHEWBACCA"]},{"s":0,"ids":["EMPERORPALPATINE","MARAJADE","VADER","GRANDADMIRALTHRAWN","DARTHMALAK"]},{"ids":["GRANDMASTERLUKE","JEDIKNIGHTLUKE","JEDIKNIGHTREVAN","GRANDMASTERYODA","HERMITYODA"],"s":1},{"s":25,"ids":["VEERS","ADMIRALPIETT","DARKTROOPER","RANGETROOPER","COLONELSTARCK"]},{"ids":["PADMEAMIDALA","BADBATCHHUNTER","BADBATCHECHO","BADBATCHTECH","BADBATCHWRECKER"],"s":31}],"787798572":[{"s":0,"ids":["GRANDMASTERLUKE","JEDIKNIGHTLUKE","JEDIKNIGHTREVAN","GRANDMASTERYODA","HERMITYODA"]},{"s":0,"ids":["COMMANDERLUKESKYWALKER","C3POLEGENDARY","HANSOLO","CHEWBACCALEGENDARY","C3POCHEWBACCA"]},{"ids":["PADMEAMIDALA","BADBATCHHUNTER","BADBATCHECHO","BADBATCHTECH","BADBATCHWRECKER"],"s":39}],"123149943":[{"ids":["VEERS","ADMIRALPIETT","DARKTROOPER","RANGETROOPER","COLONELSTARCK"],"s":25},{"ids":["COMMANDERLUKESKYWALKER","C3POLEGENDARY","HANSOLO","CHEWBACCALEGENDARY","C3POCHEWBACCA"],"s":20}],"543768742":[{"ids":["SITHPALPATINE","DARTHMALAK","DARTHMALGUS","BASTILASHANDARK","DARTHREVAN"],"s":0},{"ids":["COMMANDERLUKESKYWALKER","C3POLEGENDARY","HANSOLO","CHEWBACCALEGENDARY","C3POCHEWBACCA"],"s":0},{"s":0,"ids":["GRANDMASTERLUKE","JEDIKNIGHTLUKE","JEDIKNIGHTREVAN","GRANDMASTERYODA","HERMITYODA"]},{"s":0,"ids":["JEDIMASTERKENOBI","COMMANDERAHSOKA","GENERALKENOBI","GENERALSKYWALKER","AHSOKATANO"]},{"ids":["EMPERORPALPATINE","MARAJADE","VADER","GRANDADMIRALTHRAWN","ROYALGUARD"],"s":0},{"ids":["PADMEAMIDALA","BADBATCHHUNTER","BADBATCHECHO","BADBATCHTECH","BADBATCHWRECKER"],"s":0},{"s":4,"ids":["VEERS","ADMIRALPIETT","DARKTROOPER","RANGETROOPER","COLONELSTARCK"]}],"789344524":[{"s":0,"ids":["GRANDMASTERLUKE","JEDIKNIGHTLUKE","JEDIKNIGHTREVAN","GRANDMASTERYODA","HERMITYODA"]},{"s":0,"ids":["COMMANDERLUKESKYWALKER","C3POLEGENDARY","HANSOLO","CHEWBACCALEGENDARY","C3POCHEWBACCA"]},{"ids":["JEDIMASTERKENOBI","COMMANDERAHSOKA","GENERALKENOBI","GENERALSKYWALKER","AHSOKATANO"],"s":2}],"623628757":[{"s":0,"ids":["COMMANDERLUKESKYWALKER","C3POLEGENDARY","HANSOLO","CHEWBACCALEGENDARY","C3POCHEWBACCA"]},{"s":0,"ids":["VEERS","ADMIRALPIETT","DARKTROOPER","RANGETROOPER","MOFFGIDEONS1"]},{"s":2,"ids":["EMPERORPALPATINE","MARAJADE","VADER","GRANDADMIRALTHRAWN","DARTHMALAK"]},{"s":7,"ids":["JEDIMASTERKENOBI","COMMANDERAHSOKA","GENERALKENOBI","GENERALSKYWALKER","AHSOKATANO"]},{"ids":["PADMEAMIDALA","BADBATCHHUNTER","BADBATCHECHO","BADBATCHTECH","BADBATCHWRECKER"],"s":47},{"ids":["VEERS","ADMIRALPIETT","DARKTROOPER","RANGETROOPER","COLONELSTARCK"],"s":0},{"s":0,"ids":["GRANDMASTERLUKE","JEDIKNIGHTLUKE","JEDIKNIGHTREVAN","GRANDMASTERYODA","HERMITYODA"]}],"889188893":[{"ids":["JEDIMASTERKENOBI","COMMANDERAHSOKA","GENERALKENOBI","GENERALSKYWALKER","AHSOKATANO"],"s":0},{"s":0,"ids":["GRANDMASTERLUKE","JEDIKNIGHTLUKE","JEDIKNIGHTREVAN","GRANDMASTERYODA","HERMITYODA"]},{"ids":["EMPERORPALPATINE","MARAJADE","VADER","GRANDADMIRALTHRAWN","DARTHMALAK"],"s":0},{"s":1,"ids":["COMMANDERLUKESKYWALKER","C3POLEGENDARY","HANSOLO","CHEWBACCALEGENDARY","C3POCHEWBACCA"]},{"s":14,"ids":["VEERS","ADMIRALPIETT","DARKTROOPER","RANGETROOPER","COLONELSTARCK"]}],"834833341":[{"s":2,"ids":["JEDIMASTERKENOBI","COMMANDERAHSOKA","GENERALKENOBI","GENERALSKYWALKER","AHSOKATANO"]},{"s":3,"ids":["EMPERORPALPATINE","MARAJADE","VADER","GRANDADMIRALTHRAWN","DARTHMALAK"]},{"s":19,"ids":["VEERS","ADMIRALPIETT","DARKTROOPER","RANGETROOPER","MOFFGIDEONS1"]},{"s":24,"ids":["COMMANDERLUKESKYWALKER","C3POLEGENDARY","HANSOLO","CHEWBACCALEGENDARY","C3POCHEWBACCA"]},{"ids":["PADMEAMIDALA","BADBATCHHUNTER","BADBATCHECHO","BADBATCHTECH","BADBATCHWRECKER"],"s":41}],"748746312":[{"s":0,"ids":["GRANDMASTERLUKE","JEDIKNIGHTLUKE","JEDIKNIGHTREVAN","GRANDMASTERYODA","HERMITYODA"]},{"s":0,"ids":["COMMANDERLUKESKYWALKER","C3POLEGENDARY","HANSOLO","CHEWBACCALEGENDARY","C3POCHEWBACCA"]},{"s":15,"ids":["JEDIMASTERKENOBI","COMMANDERAHSOKA","GENERALKENOBI","GENERALSKYWALKER","AHSOKATANO"]}],"582538533":[{"s":0,"ids":["JEDIMASTERKENOBI","COMMANDERAHSOKA","GENERALKENOBI","GENERALSKYWALKER","AHSOKATANO"]},{"s":0,"ids":["EMPERORPALPATINE","MARAJADE","VADER","GRANDADMIRALTHRAWN","ROYALGUARD"]},{"ids":["VEERS","ADMIRALPIETT","DARKTROOPER","RANGETROOPER","MOFFGIDEONS1"],"s":0},{"s":0,"ids":["PADMEAMIDALA","BADBATCHHUNTER","BADBATCHECHO","BADBATCHTECH","BADBATCHWRECKER"]},{"s":15,"ids":["COMMANDERLUKESKYWALKER","C3POLEGENDARY","HANSOLO","CHEWBACCALEGENDARY","C3POCHEWBACCA"]},{"s":17,"ids":["GRANDMASTERLUKE","JEDIKNIGHTLUKE","JEDIKNIGHTREVAN","GRANDMASTERYODA","HERMITYODA"]}],"174418265":[{"ids":["JEDIMASTERKENOBI","COMMANDERAHSOKA","GENERALKENOBI","GENERALSKYWALKER","AHSOKATANO"],"s":6},{"s":24,"ids":["EMPERORPALPATINE","MARAJADE","VADER","GRANDADMIRALTHRAWN","DARTHMALAK"]},{"s":24,"ids":["COMMANDERLUKESKYWALKER","C3POLEGENDARY","HANSOLO","CHEWBACCALEGENDARY","C3POCHEWBACCA"]},{"ids":["PADMEAMIDALA","BADBATCHHUNTER","BADBATCHECHO","BADBATCHTECH","BADBATCHWRECKER"],"s":36}],"177971713":[{"ids":["COMMANDERLUKESKYWALKER","C3POLEGENDARY","HANSOLO","CHEWBACCALEGENDARY","C3POCHEWBACCA"],"s":0},{"s":1,"ids":["GRANDMASTERLUKE","JEDIKNIGHTLUKE","JEDIKNIGHTREVAN","GRANDMASTERYODA","HERMITYODA"]},{"ids":["EMPERORPALPATINE","MARAJADE","VADER","GRANDADMIRALTHRAWN","DARTHMALAK"],"s":4},{"s":24,"ids":["VEERS","ADMIRALPIETT","DARKTROOPER","RANGETROOPER","COLONELSTARCK"]},{"s":37,"ids":["PADMEAMIDALA","BADBATCHHUNTER","BADBATCHECHO","BADBATCHTECH","BADBATCHWRECKER"]}],"816945668":[{"s":0,"ids":["JEDIMASTERKENOBI","COMMANDERAHSOKA","GENERALKENOBI","GENERALSKYWALKER","AHSOKATANO"]},{"s":0,"ids":["GRANDMASTERLUKE","JEDIKNIGHTLUKE","JEDIKNIGHTREVAN","GRANDMASTERYODA","HERMITYODA"]},{"s":0,"ids":["COMMANDERLUKESKYWALKER","C3POLEGENDARY","HANSOLO","CHEWBACCALEGENDARY","C3POCHEWBACCA"]},{"ids":["EMPERORPALPATINE","MARAJADE","VADER","GRANDADMIRALTHRAWN","DARTHMALAK"],"s":11},{"ids":["VEERS","ADMIRALPIETT","DARKTROOPER","RANGETROOPER","COLONELSTARCK"],"s":8},{"s":43,"ids":["PADMEAMIDALA","BADBATCHHUNTER","BADBATCHECHO","BADBATCHTECH","BADBATCHWRECKER"]}],"394832547":[{"ids":["EMPERORPALPATINE","MARAJADE","VADER","GRANDADMIRALTHRAWN","DARTHMALAK"],"s":21},{"ids":["COMMANDERLUKESKYWALKER","C3POLEGENDARY","HANSOLO","CHEWBACCALEGENDARY","C3POCHEWBACCA"],"s":18},{"ids":["JEDIMASTERKENOBI","COMMANDERAHSOKA","GENERALKENOBI","GENERALSKYWALKER","AHSOKATANO"],"s":10},{"s":9,"ids":["GRANDMASTERLUKE","JEDIKNIGHTLUKE","JEDIKNIGHTREVAN","GRANDMASTERYODA","HERMITYODA"]}],"229516211":[{"ids":["COMMANDERLUKESKYWALKER","C3POLEGENDARY","HANSOLO","CHEWBACCALEGENDARY","C3POCHEWBACCA"],"s":0},{"s":9,"ids":["EMPERORPALPATINE","MARAJADE","VADER","GRANDADMIRALTHRAWN","DARTHMALAK"]},{"ids":["GRANDMASTERLUKE","JEDIKNIGHTLUKE","JEDIKNIGHTREVAN","GRANDMASTERYODA","HERMITYODA"],"s":19},{"s":17,"ids":["VEERS","ADMIRALPIETT","DARKTROOPER","RANGETROOPER","COLONELSTARCK"]},{"ids":["JEDIMASTERKENOBI","COMMANDERAHSOKA","GENERALKENOBI","GENERALSKYWALKER","AHSOKATANO"],"s":29},{"s":8,"ids":["VEERS","ADMIRALPIETT","DARKTROOPER","RANGETROOPER","MOFFGIDEONS1"]}],"431353962":[{"s":11,"ids":["COMMANDERLUKESKYWALKER","C3POLEGENDARY","HANSOLO","CHEWBACCALEGENDARY","C3POCHEWBACCA"]},{"ids":["EMPERORPALPATINE","MARAJADE","VADER","GRANDADMIRALTHRAWN","ROYALGUARD"],"s":21},{"ids":["PADMEAMIDALA","BADBATCHHUNTER","BADBATCHECHO","BADBATCHTECH","BADBATCHWRECKER"],"s":40},{"s":42,"ids":["VEERS","ADMIRALPIETT","DARKTROOPER","RANGETROOPER","COLONELSTARCK"]},{"ids":["EMPERORPALPATINE","MARAJADE","VADER","GRANDADMIRALTHRAWN","DARTHMALAK"],"s":20},{"ids":["VEERS","ADMIRALPIETT","DARKTROOPER","RANGETROOPER","MOFFGIDEONS1"],"s":28}],"738665898":[{"s":0,"ids":["GRANDMASTERLUKE","JEDIKNIGHTLUKE","JEDIKNIGHTREVAN","GRANDMASTERYODA","HERMITYODA"]},{"s":0,"ids":["COMMANDERLUKESKYWALKER","C3POLEGENDARY","HANSOLO","CHEWBACCALEGENDARY","C3POCHEWBACCA"]},{"ids":["EMPERORPALPATINE","MARAJADE","VADER","GRANDADMIRALTHRAWN","ROYALGUARD"],"s":2},{"ids":["PADMEAMIDALA","BADBATCHHUNTER","BADBATCHECHO","BADBATCHTECH","BADBATCHWRECKER"],"s":41},{"s":9,"ids":["JEDIMASTERKENOBI","COMMANDERAHSOKA","GENERALKENOBI","GENERALSKYWALKER","AHSOKATANO"]},{"s":25,"ids":["VEERS","ADMIRALPIETT","DARKTROOPER","RANGETROOPER","COLONELSTARCK"]}],"869191986":[{"s":3,"ids":["EMPERORPALPATINE","MARAJADE","VADER","GRANDADMIRALTHRAWN","DARTHMALAK"]},{"s":10,"ids":["COMMANDERLUKESKYWALKER","C3POLEGENDARY","HANSOLO","CHEWBACCALEGENDARY","C3POCHEWBACCA"]},{"s":40,"ids":["PADMEAMIDALA","BADBATCHHUNTER","BADBATCHECHO","BADBATCHTECH","BADBATCHWRECKER"]},{"s":40,"ids":["VEERS","ADMIRALPIETT","DARKTROOPER","RANGETROOPER","MOFFGIDEONS1"]}],"656841941":[{"s":7,"ids":["EMPERORPALPATINE","MARAJADE","VADER","GRANDADMIRALTHRAWN","DARTHMALAK"]},{"ids":["VEERS","ADMIRALPIETT","DARKTROOPER","RANGETROOPER","MOFFGIDEONS1"],"s":10},{"s":6,"ids":["COMMANDERLUKESKYWALKER","C3POLEGENDARY","HANSOLO","CHEWBACCALEGENDARY","C3POCHEWBACCA"]},{"ids":["SITHPALPATINE","DARTHMALAK","DARTHMALGUS","BASTILASHANDARK","DARTHREVAN"],"s":4},{"ids":["EMPERORPALPATINE","MARAJADE","VADER","GRANDADMIRALTHRAWN","ROYALGUARD"],"s":6},{"s":9,"ids":["JEDIMASTERKENOBI","COMMANDERAHSOKA","GENERALKENOBI","GENERALSKYWALKER","AHSOKATANO"]},{"ids":["PADMEAMIDALA","BADBATCHHUNTER","BADBATCHECHO","BADBATCHTECH","BADBATCHWRECKER"],"s":47}],"374554631":[{"ids":["COMMANDERLUKESKYWALKER","C3POLEGENDARY","HANSOLO","CHEWBACCALEGENDARY","C3POCHEWBACCA"],"s":14},{"s":35,"ids":["VEERS","ADMIRALPIETT","DARKTROOPER","RANGETROOPER","MOFFGIDEONS1"]}],"487734275":[{"s":27,"ids":["EMPERORPALPATINE","MARAJADE","VADER","GRANDADMIRALTHRAWN","DARTHMALAK"]},{"ids":["PADMEAMIDALA","BADBATCHHUNTER","BADBATCHECHO","BADBATCHTECH","BADBATCHWRECKER"],"s":37},{"ids":["COMMANDERLUKESKYWALKER","C3POLEGENDARY","HANSOLO","CHEWBACCALEGENDARY","C3POCHEWBACCA"],"s":32},{"s":49,"ids":["VEERS","ADMIRALPIETT","DARKTROOPER","RANGETROOPER","MOFFGIDEONS1"]},{"s":45,"ids":["VEERS","ADMIRALPIETT","DARKTROOPER","RANGETROOPER","COLONELSTARCK"]}],"435563797":[{"ids":["JEDIMASTERKENOBI","COMMANDERAHSOKA","GENERALKENOBI","GENERALSKYWALKER","AHSOKATANO"],"s":1},{"ids":["GRANDMASTERLUKE","JEDIKNIGHTLUKE","JEDIKNIGHTREVAN","GRANDMASTERYODA","HERMITYODA"],"s":1},{"ids":["EMPERORPALPATINE","MARAJADE","VADER","GRANDADMIRALTHRAWN","DARTHMALAK"],"s":1},{"s":2,"ids":["COMMANDERLUKESKYWALKER","C3POLEGENDARY","HANSOLO","CHEWBACCALEGENDARY","C3POCHEWBACCA"]},{"ids":["VEERS","ADMIRALPIETT","DARKTROOPER","RANGETROOPER","MOFFGIDEONS1"],"s":1},{"s":47,"ids":["PADMEAMIDALA","BADBATCHHUNTER","BADBATCHECHO","BADBATCHTECH","BADBATCHWRECKER"]}],"769349676":[{"ids":["COMMANDERLUKESKYWALKER","C3POLEGENDARY","HANSOLO","CHEWBACCALEGENDARY","C3POCHEWBACCA"],"s":0},{"ids":["GRANDMASTERLUKE","JEDIKNIGHTLUKE","JEDIKNIGHTREVAN","GRANDMASTERYODA","HERMITYODA"],"s":1},{"ids":["EMPERORPALPATINE","MARAJADE","VADER","GRANDADMIRALTHRAWN","DARTHMALAK"],"s":11}],"324122448":[{"s":0,"ids":["JEDIMASTERKENOBI","COMMANDERAHSOKA","GENERALKENOBI","GENERALSKYWALKER","AHSOKATANO"]},{"s":0,"ids":["COMMANDERLUKESKYWALKER","C3POLEGENDARY","HANSOLO","CHEWBACCALEGENDARY","C3POCHEWBACCA"]}],"476671372":[{"s":0,"ids":["JEDIMASTERKENOBI","COMMANDERAHSOKA","GENERALKENOBI","GENERALSKYWALKER","AHSOKATANO"]},{"s":0,"ids":["GRANDMASTERLUKE","JEDIKNIGHTLUKE","JEDIKNIGHTREVAN","GRANDMASTERYODA","HERMITYODA"]},{"s":0,"ids":["COMMANDERLUKESKYWALKER","C3POLEGENDARY","HANSOLO","CHEWBACCALEGENDARY","C3POCHEWBACCA"]},{"s":11,"ids":["EMPERORPALPATINE","MARAJADE","VADER","GRANDADMIRALTHRAWN","DARTHMALAK"]},{"s":42,"ids":["VEERS","ADMIRALPIETT","DARKTROOPER","RANGETROOPER","COLONELSTARCK"]},{"s":0,"ids":["SITHPALPATINE","DARTHMALAK","DARTHMALGUS","BASTILASHANDARK","DARTHREVAN"]},{"ids":["EMPERORPALPATINE","MARAJADE","VADER","GRANDADMIRALTHRAWN","ROYALGUARD"],"s":2},{"ids":["PADMEAMIDALA","BADBATCHHUNTER","BADBATCHECHO","BADBATCHTECH","BADBATCHWRECKER"],"s":44}],"221828491":[{"ids":["EMPERORPALPATINE","MARAJADE","VADER","GRANDADMIRALTHRAWN","DARTHMALAK"],"s":0},{"ids":["COMMANDERLUKESKYWALKER","C3POLEGENDARY","HANSOLO","CHEWBACCALEGENDARY","C3POCHEWBACCA"],"s":8},{"s":12,"ids":["VEERS","ADMIRALPIETT","DARKTROOPER","RANGETROOPER","COLONELSTARCK"]},{"ids":["PADMEAMIDALA","BADBATCHHUNTER","BADBATCHECHO","BADBATCHTECH","BADBATCHWRECKER"],"s":34},{"ids":["JEDIMASTERKENOBI","COMMANDERAHSOKA","GENERALKENOBI","GENERALSKYWALKER","AHSOKATANO"],"s":19},{"ids":["GRANDMASTERLUKE","JEDIKNIGHTLUKE","JEDIKNIGHTREVAN","GRANDMASTERYODA","HERMITYODA"],"s":10}],"162546989":[{"ids":["EMPERORPALPATINE","MARAJADE","VADER","GRANDADMIRALTHRAWN","DARTHMALAK"],"s":0},{"ids":["COMMANDERLUKESKYWALKER","C3POLEGENDARY","HANSOLO","CHEWBACCALEGENDARY","C3POCHEWBACCA"],"s":0}],"357873854":[{"s":0,"ids":["JEDIMASTERKENOBI","COMMANDERAHSOKA","GENERALKENOBI","GENERALSKYWALKER","AHSOKATANO"]},{"s":0,"ids":["COMMANDERLUKESKYWALKER","C3POLEGENDARY","HANSOLO","CHEWBACCALEGENDARY","C3POCHEWBACCA"]},{"ids":["EMPERORPALPATINE","MARAJADE","VADER","GRANDADMIRALTHRAWN","DARTHMALAK"],"s":1},{"s":9,"ids":["GRANDMASTERLUKE","JEDIKNIGHTLUKE","JEDIKNIGHTREVAN","GRANDMASTERYODA","HERMITYODA"]},{"s":49,"ids":["PADMEAMIDALA","BADBATCHHUNTER","BADBATCHECHO","BADBATCHTECH","BADBATCHWRECKER"]},{"s":39,"ids":["VEERS","ADMIRALPIETT","DARKTROOPER","RANGETROOPER","MOFFGIDEONS1"]},{"s":28,"ids":["VEERS","ADMIRALPIETT","DARKTROOPER","RANGETROOPER","COLONELSTARCK"]},{"ids":["SITHPALPATINE","DARTHMALAK","DARTHMALGUS","BASTILASHANDARK","DARTHREVAN"],"s":0},{"ids":["EMPERORPALPATINE","MARAJADE","VADER","GRANDADMIRALTHRAWN","ROYALGUARD"],"s":2}],"268221268":[{"s":0,"ids":["PADMEAMIDALA","BADBATCHHUNTER","BADBATCHECHO","BADBATCHTECH","BADBATCHWRECKER"]},{"ids":["COMMANDERLUKESKYWALKER","C3POLEGENDARY","HANSOLO","CHEWBACCALEGENDARY","C3POCHEWBACCA"],"s":0},{"s":2,"ids":["GRANDMASTERLUKE","JEDIKNIGHTLUKE","JEDIKNIGHTREVAN","GRANDMASTERYODA","HERMITYODA"]},{"s":9,"ids":["EMPERORPALPATINE","MARAJADE","VADER","GRANDADMIRALTHRAWN","DARTHMALAK"]},{"s":6,"ids":["VEERS","ADMIRALPIETT","DARKTROOPER","RANGETROOPER","MOFFGIDEONS1"]},{"ids":["JEDIMASTERKENOBI","COMMANDERAHSOKA","GENERALKENOBI","GENERALSKYWALKER","AHSOKATANO"],"s":9},{"s":0,"ids":["SITHPALPATINE","DARTHMALAK","DARTHMALGUS","BASTILASHANDARK","DARTHREVAN"]},{"s":0,"ids":["EMPERORPALPATINE","MARAJADE","VADER","GRANDADMIRALTHRAWN","ROYALGUARD"]}],"217249861":[{"s":0,"ids":["COMMANDERLUKESKYWALKER","C3POLEGENDARY","HANSOLO","CHEWBACCALEGENDARY","C3POCHEWBACCA"]},{"ids":["EMPERORPALPATINE","MARAJADE","VADER","GRANDADMIRALTHRAWN","ROYALGUARD"],"s":2},{"s":9,"ids":["GRANDMASTERLUKE","JEDIKNIGHTLUKE","JEDIKNIGHTREVAN","GRANDMASTERYODA","HERMITYODA"]},{"ids":["VEERS","ADMIRALPIETT","DARKTROOPER","RANGETROOPER","COLONELSTARCK"],"s":21},{"ids":["PADMEAMIDALA","BADBATCHHUNTER","BADBATCHECHO","BADBATCHTECH","BADBATCHWRECKER"],"s":26}],"911331162":[{"s":0,"ids":["JEDIMASTERKENOBI","COMMANDERAHSOKA","GENERALKENOBI","GENERALSKYWALKER","AHSOKATANO"]},{"s":0,"ids":["GRANDMASTERLUKE","JEDIKNIGHTLUKE","JEDIKNIGHTREVAN","GRANDMASTERYODA","HERMITYODA"]},{"s":0,"ids":["EMPERORPALPATINE","MARAJADE","VADER","GRANDADMIRALTHRAWN","DARTHMALAK"]},{"ids":["COMMANDERLUKESKYWALKER","C3POLEGENDARY","HANSOLO","CHEWBACCALEGENDARY","C3POCHEWBACCA"],"s":0},{"s":12,"ids":["VEERS","ADMIRALPIETT","DARKTROOPER","RANGETROOPER","MOFFGIDEONS1"]},{"ids":["SITHPALPATINE","DARTHMALAK","DARTHMALGUS","BASTILASHANDARK","DARTHREVAN"],"s":0},{"s":0,"ids":["EMPERORPALPATINE","MARAJADE","VADER","GRANDADMIRALTHRAWN","ROYALGUARD"]}],"235129274":[{"ids":["GRANDMASTERLUKE","JEDIKNIGHTLUKE","JEDIKNIGHTREVAN","GRANDMASTERYODA","HERMITYODA"],"s":0},{"ids":["COMMANDERLUKESKYWALKER","C3POLEGENDARY","HANSOLO","CHEWBACCALEGENDARY","C3POCHEWBACCA"],"s":0},{"s":0,"ids":["PADMEAMIDALA","BADBATCHHUNTER","BADBATCHECHO","BADBATCHTECH","BADBATCHWRECKER"]},{"s":9,"ids":["EMPERORPALPATINE","MARAJADE","VADER","GRANDADMIRALTHRAWN","DARTHMALAK"]},{"ids":["VEERS","ADMIRALPIETT","DARKTROOPER","RANGETROOPER","MOFFGIDEONS1"],"s":42},{"s":10,"ids":["JEDIMASTERKENOBI","COMMANDERAHSOKA","GENERALKENOBI","GENERALSKYWALKER","AHSOKATANO"]},{"s":16,"ids":["VEERS","ADMIRALPIETT","DARKTROOPER","RANGETROOPER","COLONELSTARCK"]}],"676636756":[{"s":38,"ids":["VEERS","ADMIRALPIETT","DARKTROOPER","RANGETROOPER","COLONELSTARCK"]},{"s":17,"ids":["COMMANDERLUKESKYWALKER","C3POLEGENDARY","HANSOLO","CHEWBACCALEGENDARY","C3POCHEWBACCA"]}],"776146528":[{"ids":["GRANDMASTERLUKE","JEDIKNIGHTLUKE","JEDIKNIGHTREVAN","GRANDMASTERYODA","HERMITYODA"],"s":4},{"s":2,"ids":["COMMANDERLUKESKYWALKER","C3POLEGENDARY","HANSOLO","CHEWBACCALEGENDARY","C3POCHEWBACCA"]},{"s":15,"ids":["EMPERORPALPATINE","MARAJADE","VADER","GRANDADMIRALTHRAWN","ROYALGUARD"]},{"s":34,"ids":["VEERS","ADMIRALPIETT","DARKTROOPER","RANGETROOPER","COLONELSTARCK"]},{"ids":["PADMEAMIDALA","BADBATCHHUNTER","BADBATCHECHO","BADBATCHTECH","BADBATCHWRECKER"],"s":45}],"363928881":[{"ids":["JEDIMASTERKENOBI","COMMANDERAHSOKA","GENERALKENOBI","GENERALSKYWALKER","AHSOKATANO"],"s":0},{"ids":["SITHPALPATINE","DARTHMALAK","DARTHMALGUS","BASTILASHANDARK","DARTHREVAN"],"s":0},{"ids":["GRANDMASTERLUKE","JEDIKNIGHTLUKE","JEDIKNIGHTREVAN","GRANDMASTERYODA","HERMITYODA"],"s":0},{"ids":["EMPERORPALPATINE","MARAJADE","VADER","GRANDADMIRALTHRAWN","ROYALGUARD"],"s":0},{"s":0,"ids":["COMMANDERLUKESKYWALKER","C3POLEGENDARY","HANSOLO","CHEWBACCALEGENDARY","C3POCHEWBACCA"]},{"s":0,"ids":["VEERS","ADMIRALPIETT","DARKTROOPER","RANGETROOPER","MOFFGIDEONS1"]},{"ids":["PADMEAMIDALA","BADBATCHHUNTER","BADBATCHECHO","BADBATCHTECH","BADBATCHWRECKER"],"s":0}],"595615614":[{"ids":["GRANDMASTERLUKE","JEDIKNIGHTLUKE","JEDIKNIGHTREVAN","GRANDMASTERYODA","HERMITYODA"],"s":0},{"s":0,"ids":["COMMANDERLUKESKYWALKER","C3POLEGENDARY","HANSOLO","CHEWBACCALEGENDARY","C3POCHEWBACCA"]},{"s":4,"ids":["EMPERORPALPATINE","MARAJADE","VADER","GRANDADMIRALTHRAWN","DARTHMALAK"]},{"ids":["VEERS","ADMIRALPIETT","DARKTROOPER","RANGETROOPER","COLONELSTARCK"],"s":36},{"s":23,"ids":["JEDIMASTERKENOBI","COMMANDERAHSOKA","GENERALKENOBI","GENERALSKYWALKER","AHSOKATANO"]}],"243784358":[{"ids":["GRANDMASTERLUKE","JEDIKNIGHTLUKE","JEDIKNIGHTREVAN","GRANDMASTERYODA","HERMITYODA"],"s":0},{"s":0,"ids":["PADMEAMIDALA","BADBATCHHUNTER","BADBATCHECHO","BADBATCHTECH","BADBATCHWRECKER"]},{"s":6,"ids":["EMPERORPALPATINE","MARAJADE","VADER","GRANDADMIRALTHRAWN","DARTHMALAK"]},{"ids":["COMMANDERLUKESKYWALKER","C3POLEGENDARY","HANSOLO","CHEWBACCALEGENDARY","C3POCHEWBACCA"],"s":1},{"s":0,"ids":["JEDIMASTERKENOBI","COMMANDERAHSOKA","GENERALKENOBI","GENERALSKYWALKER","AHSOKATANO"]}],"842854673":[{"s":0,"ids":["JEDIMASTERKENOBI","COMMANDERAHSOKA","GENERALKENOBI","GENERALSKYWALKER","AHSOKATANO"]},{"ids":["GRANDMASTERLUKE","JEDIKNIGHTLUKE","JEDIKNIGHTREVAN","GRANDMASTERYODA","HERMITYODA"],"s":0},{"ids":["PADMEAMIDALA","BADBATCHHUNTER","BADBATCHECHO","BADBATCHTECH","BADBATCHWRECKER"],"s":0},{"s":7,"ids":["EMPERORPALPATINE","MARAJADE","VADER","GRANDADMIRALTHRAWN","DARTHMALAK"]},{"ids":["COMMANDERLUKESKYWALKER","C3POLEGENDARY","HANSOLO","CHEWBACCALEGENDARY","C3POCHEWBACCA"],"s":2},{"s":26,"ids":["VEERS","ADMIRALPIETT","DARKTROOPER","RANGETROOPER","MOFFGIDEONS1"]},{"ids":["SITHPALPATINE","DARTHMALAK","DARTHMALGUS","BASTILASHANDARK","DARTHREVAN"],"s":0},{"ids":["EMPERORPALPATINE","MARAJADE","VADER","GRANDADMIRALTHRAWN","ROYALGUARD"],"s":0}],"449574473":[{"s":0,"ids":["EMPERORPALPATINE","MARAJADE","VADER","GRANDADMIRALTHRAWN","DARTHMALAK"]},{"ids":["GRANDMASTERLUKE","JEDIKNIGHTLUKE","JEDIKNIGHTREVAN","GRANDMASTERYODA","HERMITYODA"],"s":0},{"s":0,"ids":["COMMANDERLUKESKYWALKER","C3POLEGENDARY","HANSOLO","CHEWBACCALEGENDARY","C3POCHEWBACCA"]},{"ids":["VEERS","ADMIRALPIETT","DARKTROOPER","RANGETROOPER","MOFFGIDEONS1"],"s":9},{"s":24,"ids":["PADMEAMIDALA","BADBATCHHUNTER","BADBATCHECHO","BADBATCHTECH","BADBATCHWRECKER"]}],"268918828":[{"ids":["COMMANDERLUKESKYWALKER","C3POLEGENDARY","HANSOLO","CHEWBACCALEGENDARY","C3POCHEWBACCA"],"s":0},{"s":0,"ids":["EMPERORPALPATINE","MARAJADE","VADER","GRANDADMIRALTHRAWN","DARTHMALAK"]},{"ids":["GRANDMASTERLUKE","JEDIKNIGHTLUKE","JEDIKNIGHTREVAN","GRANDMASTERYODA","HERMITYODA"],"s":0},{"s":13,"ids":["VEERS","ADMIRALPIETT","DARKTROOPER","RANGETROOPER","MOFFGIDEONS1"]},{"s":8,"ids":["JEDIMASTERKENOBI","COMMANDERAHSOKA","GENERALKENOBI","GENERALSKYWALKER","AHSOKATANO"]}],"627665115":[{"s":0,"ids":["SITHPALPATINE","DARTHMALAK","DARTHMALGUS","BASTILASHANDARK","DARTHREVAN"]},{"s":0,"ids":["EMPERORPALPATINE","MARAJADE","VADER","GRANDADMIRALTHRAWN","ROYALGUARD"]},{"ids":["PADMEAMIDALA","BADBATCHHUNTER","BADBATCHECHO","BADBATCHTECH","BADBATCHWRECKER"],"s":0},{"ids":["VEERS","ADMIRALPIETT","DARKTROOPER","RANGETROOPER","MOFFGIDEONS1"],"s":0},{"ids":["COMMANDERLUKESKYWALKER","C3POLEGENDARY","HANSOLO","CHEWBACCALEGENDARY","C3POCHEWBACCA"],"s":25}],"495695596":[{"s":0,"ids":["JEDIMASTERKENOBI","COMMANDERAHSOKA","GENERALKENOBI","GENERALSKYWALKER","AHSOKATANO"]},{"s":0,"ids":["GRANDMASTERLUKE","JEDIKNIGHTLUKE","JEDIKNIGHTREVAN","GRANDMASTERYODA","HERMITYODA"]},{"s":0,"ids":["COMMANDERLUKESKYWALKER","C3POLEGENDARY","HANSOLO","CHEWBACCALEGENDARY","C3POCHEWBACCA"]},{"s":7,"ids":["EMPERORPALPATINE","MARAJADE","VADER","GRANDADMIRALTHRAWN","DARTHMALAK"]},{"ids":["VEERS","ADMIRALPIETT","DARKTROOPER","RANGETROOPER","MOFFGIDEONS1"],"s":24},{"ids":["PADMEAMIDALA","BADBATCHHUNTER","BADBATCHECHO","BADBATCHTECH","BADBATCHWRECKER"],"s":35},{"s":0,"ids":["SITHPALPATINE","DARTHMALAK","DARTHMALGUS","BASTILASHANDARK","DARTHREVAN"]},{"ids":["EMPERORPALPATINE","MARAJADE","VADER","GRANDADMIRALTHRAWN","ROYALGUARD"],"s":0}],"833412228":[{"ids":["EMPERORPALPATINE","MARAJADE","VADER","GRANDADMIRALTHRAWN","DARTHMALAK"],"s":0},{"s":0,"ids":["GRANDMASTERLUKE","JEDIKNIGHTLUKE","JEDIKNIGHTREVAN","GRANDMASTERYODA","HERMITYODA"]},{"ids":["COMMANDERLUKESKYWALKER","C3POLEGENDARY","HANSOLO","CHEWBACCALEGENDARY","C3POCHEWBACCA"],"s":0},{"ids":["JEDIMASTERKENOBI","COMMANDERAHSOKA","GENERALKENOBI","GENERALSKYWALKER","AHSOKATANO"],"s":6},{"s":19,"ids":["VEERS","ADMIRALPIETT","DARKTROOPER","RANGETROOPER","COLONELSTARCK"]},{"s":43,"ids":["PADMEAMIDALA","BADBATCHHUNTER","BADBATCHECHO","BADBATCHTECH","BADBATCHWRECKER"]}],"733647577":[{"ids":["EMPERORPALPATINE","MARAJADE","VADER","GRANDADMIRALTHRAWN","DARTHMALAK"],"s":0},{"s":22,"ids":["COMMANDERLUKESKYWALKER","C3POLEGENDARY","HANSOLO","CHEWBACCALEGENDARY","C3POCHEWBACCA"]},{"ids":["VEERS","ADMIRALPIETT","DARKTROOPER","RANGETROOPER","COLONELSTARCK"],"s":27},{"s":31,"ids":["PADMEAMIDALA","BADBATCHHUNTER","BADBATCHECHO","BADBATCHTECH","BADBATCHWRECKER"]}],"497555437":[{"ids":["GRANDMASTERLUKE","JEDIKNIGHTLUKE","JEDIKNIGHTREVAN","GRANDMASTERYODA","HERMITYODA"],"s":0},{"s":0,"ids":["COMMANDERLUKESKYWALKER","C3POLEGENDARY","HANSOLO","CHEWBACCALEGENDARY","C3POCHEWBACCA"]},{"ids":["EMPERORPALPATINE","MARAJADE","VADER","GRANDADMIRALTHRAWN","DARTHMALAK"],"s":16},{"ids":["PADMEAMIDALA","BADBATCHHUNTER","BADBATCHECHO","BADBATCHTECH","BADBATCHWRECKER"],"s":29},{"s":31,"ids":["VEERS","ADMIRALPIETT","DARKTROOPER","RANGETROOPER","MOFFGIDEONS1"]},{"ids":["JEDIMASTERKENOBI","COMMANDERAHSOKA","GENERALKENOBI","GENERALSKYWALKER","AHSOKATANO"],"s":10},{"ids":["VEERS","ADMIRALPIETT","DARKTROOPER","RANGETROOPER","COLONELSTARCK"],"s":17},{"ids":["SITHPALPATINE","DARTHMALAK","DARTHMALGUS","BASTILASHANDARK","DARTHREVAN"],"s":0},{"ids":["EMPERORPALPATINE","MARAJADE","VADER","GRANDADMIRALTHRAWN","ROYALGUARD"],"s":0}],"877838515":[{"ids":["GRANDMASTERLUKE","JEDIKNIGHTLUKE","JEDIKNIGHTREVAN","GRANDMASTERYODA","HERMITYODA"],"s":0},{"ids":["COMMANDERLUKESKYWALKER","C3POLEGENDARY","HANSOLO","CHEWBACCALEGENDARY","C3POCHEWBACCA"],"s":0},{"s":29,"ids":["PADMEAMIDALA","BADBATCHHUNTER","BADBATCHECHO","BADBATCHTECH","BADBATCHWRECKER"]},{"s":11,"ids":["EMPERORPALPATINE","MARAJADE","VADER","GRANDADMIRALTHRAWN","DARTHMALAK"]},{"ids":["VEERS","ADMIRALPIETT","DARKTROOPER","RANGETROOPER","COLONELSTARCK"],"s":25},{"s":10,"ids":["JEDIMASTERKENOBI","COMMANDERAHSOKA","GENERALKENOBI","GENERALSKYWALKER","AHSOKATANO"]}],"631682653":[{"ids":["EMPERORPALPATINE","MARAJADE","VADER","GRANDADMIRALTHRAWN","DARTHMALAK"],"s":9},{"s":10,"ids":["VEERS","ADMIRALPIETT","DARKTROOPER","RANGETROOPER","COLONELSTARCK"]},{"s":5,"ids":["COMMANDERLUKESKYWALKER","C3POLEGENDARY","HANSOLO","CHEWBACCALEGENDARY","C3POCHEWBACCA"]}],"145546249":[{"s":9,"ids":["EMPERORPALPATINE","MARAJADE","VADER","GRANDADMIRALTHRAWN","DARTHMALAK"]},{"s":38,"ids":["COMMANDERLUKESKYWALKER","C3POLEGENDARY","HANSOLO","CHEWBACCALEGENDARY","C3POCHEWBACCA"]},{"s":35,"ids":["VEERS","ADMIRALPIETT","DARKTROOPER","RANGETROOPER","COLONELSTARCK"]},{"ids":["SITHPALPATINE","DARTHMALAK","DARTHMALGUS","BASTILASHANDARK","DARTHREVAN"],"s":0},{"ids":["EMPERORPALPATINE","MARAJADE","VADER","GRANDADMIRALTHRAWN","ROYALGUARD"],"s":2}],"658354818":[{"s":0,"ids":["JEDIMASTERKENOBI","COMMANDERAHSOKA","GENERALKENOBI","GENERALSKYWALKER","AHSOKATANO"]},{"ids":["GRANDMASTERLUKE","JEDIKNIGHTLUKE","JEDIKNIGHTREVAN","GRANDMASTERYODA","HERMITYODA"],"s":0},{"s":0,"ids":["COMMANDERLUKESKYWALKER","C3POLEGENDARY","HANSOLO","CHEWBACCALEGENDARY","C3POCHEWBACCA"]},{"s":28,"ids":["EMPERORPALPATINE","MARAJADE","VADER","GRANDADMIRALTHRAWN","SHORETROOPER"]}],"711538869":[{"ids":["JEDIMASTERKENOBI","COMMANDERAHSOKA","GENERALKENOBI","GENERALSKYWALKER","AHSOKATANO"],"s":0},{"s":0,"ids":["GRANDMASTERLUKE","JEDIKNIGHTLUKE","JEDIKNIGHTREVAN","GRANDMASTERYODA","HERMITYODA"]},{"s":0,"ids":["EMPERORPALPATINE","MARAJADE","VADER","GRANDADMIRALTHRAWN","DARTHMALAK"]},{"ids":["PADMEAMIDALA","BADBATCHHUNTER","BADBATCHECHO","BADBATCHTECH","BADBATCHWRECKER"],"s":0},{"ids":["COMMANDERLUKESKYWALKER","C3POLEGENDARY","HANSOLO","CHEWBACCALEGENDARY","C3POCHEWBACCA"],"s":0},{"s":9,"ids":["VEERS","ADMIRALPIETT","DARKTROOPER","RANGETROOPER","MOFFGIDEONS1"]}],"849334897":[{"ids":["JEDIMASTERKENOBI","COMMANDERAHSOKA","GENERALKENOBI","GENERALSKYWALKER","AHSOKATANO"],"s":0},{"s":0,"ids":["GRANDMASTERLUKE","JEDIKNIGHTLUKE","JEDIKNIGHTREVAN","GRANDMASTERYODA","HERMITYODA"]},{"ids":["COMMANDERLUKESKYWALKER","C3POLEGENDARY","HANSOLO","CHEWBACCALEGENDARY","C3POCHEWBACCA"],"s":0},{"ids":["EMPERORPALPATINE","MARAJADE","VADER","GRANDADMIRALTHRAWN","DARTHMALAK"],"s":6},{"ids":["PADMEAMIDALA","BADBATCHHUNTER","BADBATCHECHO","BADBATCHTECH","BADBATCHWRECKER"],"s":30}],"268465663":[{"s":0,"ids":["GRANDMASTERLUKE","JEDIKNIGHTLUKE","JEDIKNIGHTREVAN","GRANDMASTERYODA","HERMITYODA"]},{"s":2,"ids":["COMMANDERLUKESKYWALKER","C3POLEGENDARY","HANSOLO","CHEWBACCALEGENDARY","C3POCHEWBACCA"]},{"ids":["EMPERORPALPATINE","MARAJADE","VADER","GRANDADMIRALTHRAWN","DARTHMALAK"],"s":6},{"s":12,"ids":["VEERS","ADMIRALPIETT","DARKTROOPER","RANGETROOPER","COLONELSTARCK"]},{"s":44,"ids":["PADMEAMIDALA","BADBATCHHUNTER","BADBATCHECHO","BADBATCHTECH","BADBATCHWRECKER"]}],"358626158":[{"ids":["JEDIMASTERKENOBI","COMMANDERAHSOKA","GENERALKENOBI","GENERALSKYWALKER","AHSOKATANO"],"s":0},{"s":0,"ids":["GRANDMASTERLUKE","JEDIKNIGHTLUKE","JEDIKNIGHTREVAN","GRANDMASTERYODA","HERMITYODA"]},{"ids":["PADMEAMIDALA","BADBATCHHUNTER","BADBATCHECHO","BADBATCHTECH","BADBATCHWRECKER"],"s":0},{"s":1,"ids":["COMMANDERLUKESKYWALKER","C3POLEGENDARY","HANSOLO","CHEWBACCALEGENDARY","C3POCHEWBACCA"]},{"s":17,"ids":["EMPERORPALPATINE","MARAJADE","VADER","GRANDADMIRALTHRAWN","DARTHMALAK"]}],"778851294":[{"ids":["GRANDMASTERLUKE","JEDIKNIGHTLUKE","JEDIKNIGHTREVAN","GRANDMASTERYODA","HERMITYODA"],"s":0},{"ids":["COMMANDERLUKESKYWALKER","C3POLEGENDARY","HANSOLO","CHEWBACCALEGENDARY","C3POCHEWBACCA"],"s":0},{"ids":["EMPERORPALPATINE","MARAJADE","VADER","GRANDADMIRALTHRAWN","DARTHMALAK"],"s":7},{"s":32,"ids":["PADMEAMIDALA","BADBATCHHUNTER","BADBATCHECHO","BADBATCHTECH","BADBATCHWRECKER"]},{"ids":["VEERS","ADMIRALPIETT","DARKTROOPER","RANGETROOPER","COLONELSTARCK"],"s":36}],"137656256":[{"ids":["GRANDMASTERLUKE","JEDIKNIGHTLUKE","JEDIKNIGHTREVAN","GRANDMASTERYODA","HERMITYODA"],"s":0},{"s":0,"ids":["COMMANDERLUKESKYWALKER","C3POLEGENDARY","HANSOLO","CHEWBACCALEGENDARY","C3POCHEWBACCA"]},{"s":36,"ids":["EMPERORPALPATINE","MARAJADE","VADER","GRANDADMIRALTHRAWN","ROYALGUARD"]},{"ids":["EMPERORPALPATINE","MARAJADE","VADER","GRANDADMIRALTHRAWN","DARTHMALAK"],"s":38},{"ids":["JEDIMASTERKENOBI","COMMANDERAHSOKA","GENERALKENOBI","GENERALSKYWALKER","AHSOKATANO"],"s":15}],"236412553":[{"s":0,"ids":["COMMANDERLUKESKYWALKER","C3POLEGENDARY","HANSOLO","CHEWBACCALEGENDARY","C3POCHEWBACCA"]},{"ids":["JEDIMASTERKENOBI","COMMANDERAHSOKA","GENERALKENOBI","GENERALSKYWALKER","AHSOKATANO"],"s":4},{"s":15,"ids":["EMPERORPALPATINE","MARAJADE","VADER","GRANDADMIRALTHRAWN","DARTHMALAK"]},{"ids":["PADMEAMIDALA","BADBATCHHUNTER","BADBATCHECHO","BADBATCHTECH","BADBATCHWRECKER"],"s":37},{"ids":["VEERS","ADMIRALPIETT","DARKTROOPER","RANGETROOPER","MOFFGIDEONS1"],"s":32},{"ids":["GRANDMASTERLUKE","JEDIKNIGHTLUKE","JEDIKNIGHTREVAN","GRANDMASTERYODA","HERMITYODA"],"s":11}],"491292939":[{"ids":["COMMANDERLUKESKYWALKER","C3POLEGENDARY","HANSOLO","CHEWBACCALEGENDARY","C3POCHEWBACCA"],"s":0},{"s":0,"ids":["EMPERORPALPATINE","MARAJADE","VADER","GRANDADMIRALTHRAWN","DARTHMALAK"]},{"ids":["PADMEAMIDALA","BADBATCHHUNTER","BADBATCHECHO","BADBATCHTECH","BADBATCHWRECKER"],"s":0},{"s":2,"ids":["GRANDMASTERLUKE","JEDIKNIGHTLUKE","JEDIKNIGHTREVAN","GRANDMASTERYODA","HERMITYODA"]},{"s":3,"ids":["JEDIMASTERKENOBI","COMMANDERAHSOKA","GENERALKENOBI","GENERALSKYWALKER","AHSOKATANO"]},{"ids":["VEERS","ADMIRALPIETT","DARKTROOPER","RANGETROOPER","COLONELSTARCK"],"s":13}],"575284166":[{"s":0,"ids":["JEDIMASTERKENOBI","COMMANDERAHSOKA","GENERALKENOBI","GENERALSKYWALKER","AHSOKATANO"]},{"ids":["VEERS","ADMIRALPIETT","DARKTROOPER","RANGETROOPER","MOFFGIDEONS1"],"s":0},{"ids":["COMMANDERLUKESKYWALKER","C3POLEGENDARY","HANSOLO","CHEWBACCALEGENDARY","C3POCHEWBACCA"],"s":0},{"ids":["PADMEAMIDALA","BADBATCHHUNTER","BADBATCHECHO","BADBATCHTECH","BADBATCHWRECKER"],"s":36},{"s":0,"ids":["SITHPALPATINE","DARTHMALAK","DARTHMALGUS","BASTILASHANDARK","DARTHREVAN"]}],"818453271":[{"s":0,"ids":["EMPERORPALPATINE","MARAJADE","VADER","GRANDADMIRALTHRAWN","DARTHMALAK"]},{"s":11,"ids":["VEERS","ADMIRALPIETT","DARKTROOPER","RANGETROOPER","MOFFGIDEONS1"]},{"s":12,"ids":["COMMANDERLUKESKYWALKER","C3POLEGENDARY","HANSOLO","CHEWBACCALEGENDARY","C3POCHEWBACCA"]}],"531828666":[{"ids":["EMPERORPALPATINE","MARAJADE","VADER","GRANDADMIRALTHRAWN","DARTHMALAK"],"s":15},{"ids":["COMMANDERLUKESKYWALKER","C3POLEGENDARY","HANSOLO","CHEWBACCALEGENDARY","C3POCHEWBACCA"],"s":22},{"s":8,"ids":["JEDIMASTERKENOBI","COMMANDERAHSOKA","GENERALKENOBI","GENERALSKYWALKER","AHSOKATANO"]},{"s":9,"ids":["GRANDMASTERLUKE","JEDIKNIGHTLUKE","JEDIKNIGHTREVAN","GRANDMASTERYODA","HERMITYODA"]},{"s":40,"ids":["PADMEAMIDALA","BADBATCHHUNTER","BADBATCHECHO","BADBATCHTECH","BADBATCHWRECKER"]}],"689764168":[{"s":0,"ids":["COMMANDERLUKESKYWALKER","C3POLEGENDARY","HANSOLO","CHEWBACCALEGENDARY","C3POCHEWBACCA"]},{"ids":["GRANDMASTERLUKE","JEDIKNIGHTLUKE","JEDIKNIGHTREVAN","GRANDMASTERYODA","HERMITYODA"],"s":21},{"s":24,"ids":["EMPERORPALPATINE","MARAJADE","VADER","GRANDADMIRALTHRAWN","DARTHMALAK"]},{"ids":["PADMEAMIDALA","BADBATCHHUNTER","BADBATCHECHO","BADBATCHTECH","BADBATCHWRECKER"],"s":24},{"ids":["VEERS","ADMIRALPIETT","DARKTROOPER","RANGETROOPER","MOFFGIDEONS1"],"s":31}],"976438777":[{"s":0,"ids":["JEDIMASTERKENOBI","COMMANDERAHSOKA","GENERALKENOBI","GENERALSKYWALKER","AHSOKATANO"]},{"s":2,"ids":["GRANDMASTERLUKE","JEDIKNIGHTLUKE","JEDIKNIGHTREVAN","GRANDMASTERYODA","HERMITYODA"]},{"s":2,"ids":["COMMANDERLUKESKYWALKER","C3POLEGENDARY","HANSOLO","CHEWBACCALEGENDARY","C3POCHEWBACCA"]}],"764254651":[{"s":0,"ids":["GRANDMASTERLUKE","JEDIKNIGHTLUKE","JEDIKNIGHTREVAN","GRANDMASTERYODA","HERMITYODA"]},{"s":0,"ids":["COMMANDERLUKESKYWALKER","C3POLEGENDARY","HANSOLO","CHEWBACCALEGENDARY","C3POCHEWBACCA"]},{"s":30,"ids":["VEERS","ADMIRALPIETT","DARKTROOPER","RANGETROOPER","COLONELSTARCK"]},{"s":9,"ids":["EMPERORPALPATINE","MARAJADE","VADER","GRANDADMIRALTHRAWN","DARTHMALAK"]},{"s":38,"ids":["PADMEAMIDALA","BADBATCHHUNTER","BADBATCHECHO","BADBATCHTECH","BADBATCHWRECKER"]},{"s":11,"ids":["JEDIMASTERKENOBI","COMMANDERAHSOKA","GENERALKENOBI","GENERALSKYWALKER","AHSOKATANO"]},{"s":31,"ids":["VEERS","ADMIRALPIETT","DARKTROOPER","RANGETROOPER","MOFFGIDEONS1"]}],"824796359":[{"ids":["JEDIMASTERKENOBI","COMMANDERAHSOKA","GENERALKENOBI","GENERALSKYWALKER","AHSOKATANO"],"s":0},{"ids":["GRANDMASTERLUKE","JEDIKNIGHTLUKE","JEDIKNIGHTREVAN","GRANDMASTERYODA","HERMITYODA"],"s":0},{"ids":["COMMANDERLUKESKYWALKER","C3POLEGENDARY","HANSOLO","CHEWBACCALEGENDARY","C3POCHEWBACCA"],"s":0},{"s":11,"ids":["EMPERORPALPATINE","MARAJADE","VADER","GRANDADMIRALTHRAWN","DARTHMALAK"]},{"ids":["VEERS","ADMIRALPIETT","DARKTROOPER","RANGETROOPER","MOFFGIDEONS1"],"s":37},{"ids":["PADMEAMIDALA","BADBATCHHUNTER","BADBATCHECHO","BADBATCHTECH","BADBATCHWRECKER"],"s":39}],"934725681":[{"s":0,"ids":["GRANDMASTERLUKE","JEDIKNIGHTLUKE","JEDIKNIGHTREVAN","GRANDMASTERYODA","HERMITYODA"]},{"s":0,"ids":["COMMANDERLUKESKYWALKER","C3POLEGENDARY","HANSOLO","CHEWBACCALEGENDARY","C3POCHEWBACCA"]},{"s":6,"ids":["EMPERORPALPATINE","MARAJADE","VADER","GRANDADMIRALTHRAWN","DARTHMALAK"]},{"ids":["VEERS","ADMIRALPIETT","DARKTROOPER","RANGETROOPER","COLONELSTARCK"],"s":24},{"ids":["PADMEAMIDALA","BADBATCHHUNTER","BADBATCHECHO","BADBATCHTECH","BADBATCHWRECKER"],"s":36}],"888783572":[{"ids":["GRANDMASTERLUKE","JEDIKNIGHTLUKE","JEDIKNIGHTREVAN","GRANDMASTERYODA","HERMITYODA"],"s":0},{"ids":["COMMANDERLUKESKYWALKER","C3POLEGENDARY","HANSOLO","CHEWBACCALEGENDARY","C3POCHEWBACCA"],"s":0},{"ids":["EMPERORPALPATINE","MARAJADE","VADER","GRANDADMIRALTHRAWN","DARTHMALAK"],"s":0},{"ids":["PADMEAMIDALA","BADBATCHHUNTER","BADBATCHECHO","BADBATCHTECH","BADBATCHWRECKER"],"s":0},{"s":1,"ids":["JEDIMASTERKENOBI","COMMANDERAHSOKA","GENERALKENOBI","GENERALSKYWALKER","AHSOKATANO"]},{"s":26,"ids":["VEERS","ADMIRALPIETT","DARKTROOPER","RANGETROOPER","COLONELSTARCK"]}],"427459795":[{"s":7,"ids":["EMPERORPALPATINE","MARAJADE","VADER","GRANDADMIRALTHRAWN","DARTHMALAK"]},{"s":15,"ids":["JEDIMASTERKENOBI","COMMANDERAHSOKA","GENERALKENOBI","GENERALSKYWALKER","AHSOKATANO"]},{"ids":["SITHPALPATINE","DARTHMALAK","DARTHMALGUS","BASTILASHANDARK","DARTHREVAN"],"s":9},{"s":7,"ids":["EMPERORPALPATINE","MARAJADE","VADER","GRANDADMIRALTHRAWN","ROYALGUARD"]},{"s":37,"ids":["PADMEAMIDALA","BADBATCHHUNTER","BADBATCHECHO","BADBATCHTECH","BADBATCHWRECKER"]},{"s":19,"ids":["VEERS","ADMIRALPIETT","DARKTROOPER","RANGETROOPER","COLONELSTARCK"]},{"s":6,"ids":["COMMANDERLUKESKYWALKER","C3POLEGENDARY","HANSOLO","CHEWBACCALEGENDARY","C3POCHEWBACCA"]}],"664471259":[{"ids":["PADMEAMIDALA","BADBATCHHUNTER","BADBATCHECHO","BADBATCHTECH","BADBATCHWRECKER"],"s":0},{"s":30,"ids":["VEERS","ADMIRALPIETT","DARKTROOPER","RANGETROOPER","COLONELSTARCK"]},{"s":17,"ids":["COMMANDERLUKESKYWALKER","C3POLEGENDARY","HANSOLO","CHEWBACCALEGENDARY","C3POCHEWBACCA"]},{"s":13,"ids":["GRANDMASTERLUKE","JEDIKNIGHTLUKE","JEDIKNIGHTREVAN","GRANDMASTERYODA","HERMITYODA"]},{"s":18,"ids":["JEDIMASTERKENOBI","COMMANDERAHSOKA","GENERALKENOBI","GENERALSKYWALKER","AHSOKATANO"]},{"ids":["EMPERORPALPATINE","MARAJADE","VADER","GRANDADMIRALTHRAWN","ROYALGUARD"],"s":9}],"614987169":[{"s":0,"ids":["JEDIMASTERKENOBI","COMMANDERAHSOKA","GENERALKENOBI","GENERALSKYWALKER","AHSOKATANO"]},{"ids":["EMPERORPALPATINE","MARAJADE","VADER","GRANDADMIRALTHRAWN","ROYALGUARD"],"s":0},{"ids":["SITHPALPATINE","DARTHMALAK","DARTHMALGUS","BASTILASHANDARK","DARTHREVAN"],"s":0},{"ids":["PADMEAMIDALA","BADBATCHHUNTER","BADBATCHECHO","BADBATCHTECH","BADBATCHWRECKER"],"s":0},{"s":0,"ids":["COMMANDERLUKESKYWALKER","C3POLEGENDARY","HANSOLO","CHEWBACCALEGENDARY","C3POCHEWBACCA"]},{"ids":["GRANDMASTERLUKE","JEDIKNIGHTLUKE","JEDIKNIGHTREVAN","GRANDMASTERYODA","HERMITYODA"],"s":2},{"s":14,"ids":["VEERS","ADMIRALPIETT","DARKTROOPER","RANGETROOPER","COLONELSTARCK"]}],"917631287":[{"s":0,"ids":["GRANDMASTERLUKE","JEDIKNIGHTLUKE","JEDIKNIGHTREVAN","GRANDMASTERYODA","HERMITYODA"]},{"s":0,"ids":["COMMANDERLUKESKYWALKER","C3POLEGENDARY","HANSOLO","CHEWBACCALEGENDARY","C3POCHEWBACCA"]},{"s":20,"ids":["EMPERORPALPATINE","MARAJADE","VADER","GRANDADMIRALTHRAWN","ROYALGUARD"]},{"s":40,"ids":["VEERS","ADMIRALPIETT","DARKTROOPER","RANGETROOPER","COLONELSTARCK"]}],"598114161":[{"ids":["COMMANDERLUKESKYWALKER","C3POLEGENDARY","HANSOLO","CHEWBACCALEGENDARY","C3POCHEWBACCA"],"s":0},{"s":0,"ids":["GRANDMASTERLUKE","JEDIKNIGHTLUKE","JEDIKNIGHTREVAN","GRANDMASTERYODA","HERMITYODA"]},{"ids":["PADMEAMIDALA","BADBATCHHUNTER","BADBATCHECHO","BADBATCHTECH","BADBATCHWRECKER"],"s":0},{"s":2,"ids":["JEDIMASTERKENOBI","COMMANDERAHSOKA","GENERALKENOBI","GENERALSKYWALKER","AHSOKATANO"]},{"ids":["EMPERORPALPATINE","MARAJADE","VADER","GRANDADMIRALTHRAWN","ROYALGUARD"],"s":2},{"s":27,"ids":["VEERS","ADMIRALPIETT","DARKTROOPER","RANGETROOPER","COLONELSTARCK"]},{"ids":["SITHPALPATINE","DARTHMALAK","DARTHMALGUS","BASTILASHANDARK","DARTHREVAN"],"s":16}],"486623434":[{"ids":["JEDIMASTERKENOBI","COMMANDERAHSOKA","GENERALKENOBI","GENERALSKYWALKER","AHSOKATANO"],"s":0},{"s":0,"ids":["VEERS","ADMIRALPIETT","DARKTROOPER","RANGETROOPER","MOFFGIDEONS1"]},{"s":0,"ids":["PADMEAMIDALA","BADBATCHHUNTER","BADBATCHECHO","BADBATCHTECH","BADBATCHWRECKER"]},{"ids":["EMPERORPALPATINE","MARAJADE","VADER","GRANDADMIRALTHRAWN","ROYALGUARD"],"s":6},{"s":10,"ids":["COMMANDERLUKESKYWALKER","C3POLEGENDARY","HANSOLO","CHEWBACCALEGENDARY","C3POCHEWBACCA"]},{"s":14,"ids":["SITHPALPATINE","DARTHMALAK","DARTHMALGUS","BASTILASHANDARK","DARTHREVAN"]}],"336411921":[{"s":0,"ids":["COMMANDERLUKESKYWALKER","C3POLEGENDARY","HANSOLO","CHEWBACCALEGENDARY","C3POCHEWBACCA"]},{"ids":["GRANDMASTERLUKE","JEDIKNIGHTLUKE","JEDIKNIGHTREVAN","GRANDMASTERYODA","HERMITYODA"],"s":6},{"s":22,"ids":["EMPERORPALPATINE","MARAJADE","VADER","GRANDADMIRALTHRAWN","DARTHMALAK"]},{"ids":["VEERS","ADMIRALPIETT","DARKTROOPER","RANGETROOPER","COLONELSTARCK"],"s":35},{"ids":["PADMEAMIDALA","BADBATCHHUNTER","BADBATCHECHO","BADBATCHTECH","BADBATCHWRECKER"],"s":40},{"s":23,"ids":["JEDIMASTERKENOBI","COMMANDERAHSOKA","GENERALKENOBI","GENERALSKYWALKER","AHSOKATANO"]}],"187668216":[{"ids":["JEDIMASTERKENOBI","COMMANDERAHSOKA","GENERALKENOBI","GENERALSKYWALKER","AHSOKATANO"],"s":0},{"ids":["GRANDMASTERLUKE","JEDIKNIGHTLUKE","JEDIKNIGHTREVAN","GRANDMASTERYODA","HERMITYODA"],"s":0},{"s":0,"ids":["COMMANDERLUKESKYWALKER","C3POLEGENDARY","HANSOLO","CHEWBACCALEGENDARY","C3POCHEWBACCA"]},{"ids":["EMPERORPALPATINE","MARAJADE","VADER","GRANDADMIRALTHRAWN","DARTHMALAK"],"s":9},{"ids":["VEERS","ADMIRALPIETT","DARKTROOPER","RANGETROOPER","COLONELSTARCK"],"s":26},{"s":37,"ids":["PADMEAMIDALA","BADBATCHHUNTER","BADBATCHECHO","BADBATCHTECH","BADBATCHWRECKER"]},{"ids":["SITHPALPATINE","DARTHMALAK","DARTHMALGUS","BASTILASHANDARK","DARTHREVAN"],"s":9},{"s":9,"ids":["EMPERORPALPATINE","MARAJADE","VADER","GRANDADMIRALTHRAWN","ROYALGUARD"]}],"438482477":[{"s":0,"ids":["JEDIMASTERKENOBI","COMMANDERAHSOKA","GENERALKENOBI","GENERALSKYWALKER","AHSOKATANO"]},{"s":0,"ids":["EMPERORPALPATINE","MARAJADE","VADER","GRANDADMIRALTHRAWN","DARTHMALAK"]},{"ids":["VEERS","ADMIRALPIETT","DARKTROOPER","RANGETROOPER","COLONELSTARCK"],"s":15},{"ids":["PADMEAMIDALA","BADBATCHHUNTER","BADBATCHECHO","BADBATCHTECH","BADBATCHWRECKER"],"s":8},{"s":21,"ids":["COMMANDERLUKESKYWALKER","C3POLEGENDARY","HANSOLO","CHEWBACCALEGENDARY","C3POCHEWBACCA"]}]}}