{"data":{"754964832":[{"s":6,"ids":["COUNTDOOKU","ASAJVENTRESS"]},{"ids":["GEONOSIANBROODALPHA","POGGLETHELESSER","GEONOSIANSOLDIER","SUNFAC","GEONOSIANSPY"],"s":1}],"999729325":[{"ids":["GRIEVOUS","B2SUPERBATTLEDROID","B1BATTLEDROIDV2","DROIDEKA","MAGNAGUARD"],"s":0},{"ids":["COUNTDOOKU","ASAJVENTRESS"],"s":0},{"ids":["GEONOSIANBROODALPHA","POGGLETHELESSER","GEONOSIANSOLDIER","SUNFAC","GEONOSIANSPY"],"s":0}],"665383812":[{"ids":["GEONOSIANBROODALPHA","POGGLETHELESSER","GEONOSIANSOLDIER","SUNFAC","GEONOSIANSPY"],"s":0},{"ids":["COUNTDOOKU","ASAJVENTRESS"],"s":10}],"862655434":[{"s":0,"ids":["GRIEVOUS","B2SUPERBATTLEDROID","B1BATTLEDROIDV2","DROIDEKA","MAGNAGUARD"]},{"ids":["COUNTDOOKU","ASAJVENTRESS"],"s":0},{"s":0,"ids":["GEONOSIANBROODALPHA","POGGLETHELESSER","GEONOSIANSOLDIER","SUNFAC","GEONOSIANSPY"]},{"s":5,"ids":["VEERS","ADMIRALPIETT","COLONELSTARCK","DARKTROOPER","RANGETROOPER"]}],"479523636":[{"s":0,"ids":["GRIEVOUS","B2SUPERBATTLEDROID","B1BATTLEDROIDV2","DROIDEKA","MAGNAGUARD"]},{"s":0,"ids":["COUNTDOOKU","ASAJVENTRESS"]},{"s":0,"ids":["GEONOSIANBROODALPHA","POGGLETHELESSER","GEONOSIANSOLDIER","SUNFAC","GEONOSIANSPY"]}]}}